MANIFEST.in
README.md
setup.py
hierarchical_classifier/__init__.py
hierarchical_classifier/hierarchical_classifier.py
hierarchical_classifier.egg-info/Icon
hierarchical_classifier.egg-info/PKG-INFO
hierarchical_classifier.egg-info/SOURCES.txt
hierarchical_classifier.egg-info/dependency_links.txt
hierarchical_classifier.egg-info/requires.txt
hierarchical_classifier.egg-info/top_level.txt