Metadata-Version: 1.0
Name: hierarchical-classifier
Version: 2020.5.20a0
Summary: Customizable scikit-learn compatible hierarchical classifiers
Home-page: https://github.com/jolespin/hierarchical_classifier
Author: Josh L. Espinoza
Author-email: jespinoz@jcvi.org
License: BSD-3
Platform: UNKNOWN
